<?xml version="1.0" encoding="UTF-8"?>
<codehawk-java-analyzer>
  <header info="interface" time="2019-01-16 18:17:37"/>
  <interface name="ViewDisplay" package="com.vaadin.navigator">
    <superinterfaces>
      <superinterface>java.io.Serializable</superinterface>
    </superinterfaces>
    <!-- ============================== METHODS ==============================  -->
    <methods>
      <!-- ~~~~~~~~~~~~~~~~~~~~~~~~~~~~~~~~~~~~~~~~~~~~~~~~~~~~~~~~~~~~ showView -->
      <method abstract="yes" access="public" name="showView">
        <signature>
          <arg nr="1">
            <object>com.vaadin.navigator.View</object>
          </arg>
        </signature>
        <exceptions/>
        <summary/>
      </method>
    </methods>
  </interface>
  <copyright-notice>Copyright 2012-2019, Kestrel Technology LLC, Palo Alto, CA 94304</copyright-notice>
</codehawk-java-analyzer>
