<?xml version="1.0" encoding="UTF-8"?>
<codehawk-java-analyzer>
  <header info="class" time="2019-01-16 18:00:10"/>
  <class name="Component$Event" package="com.vaadin.ui">
    <superclass>com.vaadin.event.ConnectorEvent</superclass>
    <interfaces>
      <implements>java.io.Serializable</implements>
    </interfaces>
    <!-- =============================== FIELDS ===============================  -->
    <fields>
      <!-- ~~~~~~~~~~~~~~~~~~~~~~~~~~~~~~~~~~ (inherited) field:serialVersionUID -->
      <field from="java.util.EventObject" inherited="yes" name="serialVersionUID">
        <signature>
          <long/>
        </signature>
      </field>
      <!-- ~~~~~~~~~~~~~~~~~~~~~~~~~~~~~~~~~~~~~~~~~~~~ (inherited) field:source -->
      <field from="java.util.EventObject" inherited="yes" name="source">
        <signature>
          <object>java.lang.Object</object>
        </signature>
      </field>
    </fields>
    <!-- ============================ CONSTRUCTORS ============================  -->
    <constructors>
      <!-- ~~~~~~~~~~~~~~~~~~~~~~~~~~~~~~~~~~~~~~~~~~~ (com.vaadin.ui.Component) -->
      <method access="public" instrs="4" valid="no">
        <signature>
          <arg nr="1">
            <object>com.vaadin.ui.Component</object>
          </arg>
        </signature>
        <exceptions/>
        <summary/>
      </method>
    </constructors>
    <!-- ============================== METHODS ==============================  -->
    <methods>
      <!-- ~~~~~~~~~~~~~~~~~~~~~~~~~~~~~~~~~~~~~~~~~~~~~~~~~~~~~~~~ getComponent -->
      <method access="public" instrs="4" name="getComponent" valid="no">
        <signature>
          <return>
            <object>com.vaadin.ui.Component</object>
          </return>
        </signature>
        <exceptions/>
        <summary/>
      </method>
    </methods>
  </class>
  <copyright-notice>Copyright 2012-2019, Kestrel Technology LLC, Palo Alto, CA 94304</copyright-notice>
</codehawk-java-analyzer>
