<?xml version="1.0" encoding="UTF-8"?>
<codehawk-java-analyzer>
  <header info="class" time="2019-01-17 18:50:44"/>
  <class abstract="yes" name="BaseTestRunner" package="junit.runner">
    <interfaces>
      <implements>junit.framework.TestListener</implements>
    </interfaces>
    <!-- =============================== FIELDS ===============================  -->
    <fields>
      <!-- ~~~~~~~~~~~~~~~~~~~~~~~~~~~~~~~~~~~~~~~~~~~~~~ field:SUITE_METHODNAME -->
      <field access="public" final="yes" name="SUITE_METHODNAME" not-null="yes" static="yes">
        <signature>
          <object>java.lang.String</object>
        </signature>
        <value>
          <string value="suite"/>
        </value>
      </field>
      <!-- ~~~~~~~~~~~~~~~~~~~~~~~~~~~~~~~~~~~~~~~~~~~~~~~~~~ field:fPreferences -->
      <field access="private" name="fPreferences" static="yes">
        <signature>
          <object>java.util.Properties</object>
        </signature>
      </field>
      <!-- ~~~~~~~~~~~~~~~~~~~~~~~~~~~~~~~~~~~~~~~~~~~~ field:fgMaxMessageLength -->
      <field access="default" name="fgMaxMessageLength" static="yes">
        <signature>
          <int/>
        </signature>
      </field>
      <!-- ~~~~~~~~~~~~~~~~~~~~~~~~~~~~~~~~~~~~~~~~~~~~~~~~~ field:fgFilterStack -->
      <field access="default" name="fgFilterStack" static="yes">
        <signature>
          <boolean/>
        </signature>
      </field>
      <!-- ~~~~~~~~~~~~~~~~~~~~~~~~~~~~~~~~~~~~~~~~~~~~~~~~~~~~~~ field:fLoading -->
      <field access="default" name="fLoading">
        <signature>
          <boolean/>
        </signature>
      </field>
    </fields>
    <!-- ============================ CONSTRUCTORS ============================  -->
    <constructors>
      <!-- ~~~~~~~~~~~~~~~~~~~~~~~~~~~~~~~~~~~~~~~~~~~~~~~~~~~~~~~~~~~~~~~~~~ () -->
      <method access="public" instrs="6" valid="no">
        <signature/>
        <exceptions/>
        <summary/>
      </method>
    </constructors>
    <!-- ============================== METHODS ==============================  -->
    <methods>
      <!-- ~~~~~~~~~~~~~~~~~~~~~~~~~~~~~~~~~~~~~~~~~~~~~~~~~~~~~~~~~~~~ addError -->
      <method access="public" instrs="6" name="addError" valid="no">
        <signature>
          <arg nr="1">
            <object>junit.framework.Test</object>
          </arg>
          <arg nr="2">
            <object>java.lang.Throwable</object>
          </arg>
        </signature>
        <exceptions/>
        <summary/>
      </method>
      <!-- ~~~~~~~~~~~~~~~~~~~~~~~~~~~~~~~~~~~~~~~~~~~~~~~~~~~~~~~~~~ addFailure -->
      <method access="public" instrs="6" name="addFailure" valid="no">
        <signature>
          <arg nr="1">
            <object>junit.framework.Test</object>
          </arg>
          <arg nr="2">
            <object>junit.framework.AssertionFailedError</object>
          </arg>
        </signature>
        <exceptions/>
        <summary/>
      </method>
      <!-- ~~~~~~~~~~~~~~~~~~~~~~~~~~~~~~~~~~~~~~~~~~~~~~~~~~~~~~~~~ clearStatus -->
      <method access="protected" instrs="1" name="clearStatus" valid="no">
        <signature/>
        <exceptions/>
        <summary/>
      </method>
      <!-- ~~~~~~~~~~~~~~~~~~~~~~~~~~~~~~~~~~~~~~~~~~~~~~~~~ elapsedTimeAsString -->
      <method access="public" instrs="7" name="elapsedTimeAsString" valid="no">
        <signature>
          <arg nr="1">
            <long/>
          </arg>
          <return>
            <object>java.lang.String</object>
          </return>
        </signature>
        <exceptions/>
        <summary/>
      </method>
      <!-- ~~~~~~~~~~~~~~~~~~~~~~~~~~~~~~~~~~~~~~~~~~~~~~~~~~~~~~~~~~~~~ endTest -->
      <method access="public" instrs="5" name="endTest" valid="no">
        <signature>
          <arg nr="1">
            <object>junit.framework.Test</object>
          </arg>
        </signature>
        <exceptions/>
        <summary/>
      </method>
      <!-- ~~~~~~~~~~~~~~~~~~~~~~~~~~~~~~~~~~~~~~~~~~~~~~~~~~~~ extractClassName -->
      <method access="public" instrs="14" name="extractClassName" valid="no">
        <signature>
          <arg nr="1">
            <object>java.lang.String</object>
          </arg>
          <return>
            <object>java.lang.String</object>
          </return>
        </signature>
        <exceptions/>
        <summary/>
      </method>
      <!-- ~~~~~~~~~~~~~~~~~~~~~~~~~~~~~~~~~~~~~~~~~~~~~~~~~~~~~~~~~~ filterLine -->
      <method access="default" instrs="53" name="filterLine" static="yes" valid="no">
        <signature>
          <arg nr="1">
            <object>java.lang.String</object>
          </arg>
          <return>
            <boolean/>
          </return>
        </signature>
        <exceptions/>
        <summary/>
      </method>
      <!-- ~~~~~~~~~~~~~~~~~~~~~~~~~~~~~~~~~~~~~~~~~~~~~~~~~~~~ getFilteredTrace -->
      <method access="public" instrs="21" name="getFilteredTrace" static="yes" valid="no">
        <signature>
          <arg nr="1">
            <object>java.lang.Throwable</object>
          </arg>
          <return>
            <object>java.lang.String</object>
          </return>
        </signature>
        <exceptions/>
        <summary/>
      </method>
      <!-- ~~~~~~~~~~~~~~~~~~~~~~~~~~~~~~~~~~~~~~~~~~~~~~~~~~~~ getFilteredTrace -->
      <method access="public" instrs="42" name="getFilteredTrace" static="yes" valid="no">
        <signature>
          <arg nr="1">
            <object>java.lang.String</object>
          </arg>
          <return>
            <object>java.lang.String</object>
          </return>
        </signature>
        <exceptions/>
        <summary/>
      </method>
      <!-- ~~~~~~~~~~~~~~~~~~~~~~~~~~~~~~~~~~~~~~~~~~~~~~~~~~~~~~~ getPreference -->
      <method access="public" instrs="4" name="getPreference" static="yes" valid="no">
        <signature>
          <arg nr="1">
            <object>java.lang.String</object>
          </arg>
          <return>
            <object>java.lang.String</object>
          </return>
        </signature>
        <exceptions/>
        <summary/>
      </method>
      <!-- ~~~~~~~~~~~~~~~~~~~~~~~~~~~~~~~~~~~~~~~~~~~~~~~~~~~~~~~ getPreference -->
      <method access="public" instrs="16" name="getPreference" static="yes" valid="no">
        <signature>
          <arg nr="1">
            <object>java.lang.String</object>
          </arg>
          <arg nr="2">
            <int/>
          </arg>
          <return>
            <int/>
          </return>
        </signature>
        <exceptions/>
        <summary/>
      </method>
      <!-- ~~~~~~~~~~~~~~~~~~~~~~~~~~~~~~~~~~~~~~~~~~~~~~~~~~~~~~ getPreferences -->
      <method access="protected" instrs="19" name="getPreferences" static="yes" valid="no">
        <signature>
          <return>
            <object>java.util.Properties</object>
          </return>
        </signature>
        <exceptions/>
        <summary/>
      </method>
      <!-- ~~~~~~~~~~~~~~~~~~~~~~~~~~~~~~~~~~~~~~~~~~~~~~~~~~ getPreferencesFile -->
      <method access="private" instrs="9" name="getPreferencesFile" static="yes" valid="no">
        <signature>
          <return>
            <object>java.io.File</object>
          </return>
        </signature>
        <exceptions/>
        <summary/>
      </method>
      <!-- ~~~~~~~~~~~~~~~~~~~~~~~~~~~~~~~~~~~~~~~~~~~~~~~~~~~~~~~~~~~~~ getTest -->
      <method access="public" instrs="124" name="getTest" valid="no">
        <signature>
          <arg nr="1">
            <object>java.lang.String</object>
          </arg>
          <return>
            <object>junit.framework.Test</object>
          </return>
        </signature>
        <exceptions/>
        <summary/>
      </method>
      <!-- ~~~~~~~~~~~~~~~~~~~~~~~~~~~~~~~~~~~~~~~~~~~~~~~~~~~~~~ loadSuiteClass -->
      <method access="protected" instrs="3" name="loadSuiteClass" valid="no">
        <signature>
          <arg nr="1">
            <object>java.lang.String</object>
          </arg>
          <return>
            <object>java.lang.Class</object>
          </return>
        </signature>
        <exceptions>
          <throws>java.lang.ClassNotFoundException</throws>
          <throws>java.lang.ClassNotFoundException</throws>
        </exceptions>
        <summary/>
      </method>
      <!-- ~~~~~~~~~~~~~~~~~~~~~~~~~~~~~~~~~~~~~~~~~~~~~~~~~~~~ processArguments -->
      <method access="protected" instrs="61" name="processArguments" valid="no">
        <signature>
          <arg nr="1">
            <array>
              <object>java.lang.String</object>
            </array>
          </arg>
          <return>
            <object>java.lang.String</object>
          </return>
        </signature>
        <exceptions/>
        <summary/>
      </method>
      <!-- ~~~~~~~~~~~~~~~~~~~~~~~~~~~~~~~~~~~~~~~~~~~~~~~~~~~~~ readPreferences -->
      <method access="private" instrs="24" name="readPreferences" static="yes" valid="no">
        <signature/>
        <exceptions/>
        <summary/>
      </method>
      <!-- ~~~~~~~~~~~~~~~~~~~~~~~~~~~~~~~~~~~~~~~~~~~~~~~~~~~~~~~~~~~ runFailed -->
      <method abstract="yes" access="protected" name="runFailed" valid="no">
        <signature>
          <arg nr="1">
            <object>java.lang.String</object>
          </arg>
        </signature>
        <exceptions/>
        <summary/>
      </method>
      <!-- ~~~~~~~~~~~~~~~~~~~~~~~~~~~~~~~~~~~~~~~~~~~~~~~~~~~~~ savePreferences -->
      <method access="public" instrs="18" name="savePreferences" static="yes" valid="no">
        <signature/>
        <exceptions>
          <throws>java.io.IOException</throws>
          <throws>java.io.IOException</throws>
        </exceptions>
        <summary/>
      </method>
      <!-- ~~~~~~~~~~~~~~~~~~~~~~~~~~~~~~~~~~~~~~~~~~~~~~~~~~~~~~~~~~ setLoading -->
      <method access="public" instrs="4" name="setLoading" valid="no">
        <signature>
          <arg nr="1">
            <boolean/>
          </arg>
        </signature>
        <exceptions/>
        <summary/>
      </method>
      <!-- ~~~~~~~~~~~~~~~~~~~~~~~~~~~~~~~~~~~~~~~~~~~~~~~~~~~~~~~ setPreference -->
      <method access="public" instrs="6" name="setPreference" static="yes" valid="no">
        <signature>
          <arg nr="1">
            <object>java.lang.String</object>
          </arg>
          <arg nr="2">
            <object>java.lang.String</object>
          </arg>
        </signature>
        <exceptions/>
        <summary/>
      </method>
      <!-- ~~~~~~~~~~~~~~~~~~~~~~~~~~~~~~~~~~~~~~~~~~~~~~~~~~~~~~ setPreferences -->
      <method access="protected" instrs="3" name="setPreferences" static="yes" valid="no">
        <signature>
          <arg nr="1">
            <object>java.util.Properties</object>
          </arg>
        </signature>
        <exceptions/>
        <summary/>
      </method>
      <!-- ~~~~~~~~~~~~~~~~~~~~~~~~~~~~~~~~~~~~~~~~~~~~~~~~~~~~~~~~ showStackRaw -->
      <method access="protected" instrs="11" name="showStackRaw" static="yes" valid="no">
        <signature>
          <return>
            <boolean/>
          </return>
        </signature>
        <exceptions/>
        <summary/>
      </method>
      <!-- ~~~~~~~~~~~~~~~~~~~~~~~~~~~~~~~~~~~~~~~~~~~~~~~~~~~~~~~~~~~ startTest -->
      <method access="public" instrs="5" name="startTest" valid="no">
        <signature>
          <arg nr="1">
            <object>junit.framework.Test</object>
          </arg>
        </signature>
        <exceptions/>
        <summary/>
      </method>
      <!-- ~~~~~~~~~~~~~~~~~~~~~~~~~~~~~~~~~~~~~~~~~~~~~~~~~~~~~~~~~~~ testEnded -->
      <method abstract="yes" access="public" name="testEnded" valid="no">
        <signature>
          <arg nr="1">
            <object>java.lang.String</object>
          </arg>
        </signature>
        <exceptions/>
        <summary/>
      </method>
      <!-- ~~~~~~~~~~~~~~~~~~~~~~~~~~~~~~~~~~~~~~~~~~~~~~~~~~~~~~~~~~ testFailed -->
      <method abstract="yes" access="public" name="testFailed" valid="no">
        <signature>
          <arg nr="1">
            <int/>
          </arg>
          <arg nr="2">
            <object>junit.framework.Test</object>
          </arg>
          <arg nr="3">
            <object>java.lang.Throwable</object>
          </arg>
        </signature>
        <exceptions/>
        <summary/>
      </method>
      <!-- ~~~~~~~~~~~~~~~~~~~~~~~~~~~~~~~~~~~~~~~~~~~~~~~~~~~~~~~~~ testStarted -->
      <method abstract="yes" access="public" name="testStarted" valid="no">
        <signature>
          <arg nr="1">
            <object>java.lang.String</object>
          </arg>
        </signature>
        <exceptions/>
        <summary/>
      </method>
      <!-- ~~~~~~~~~~~~~~~~~~~~~~~~~~~~~~~~~~~~~~~~~~~~~~~~~~~~~~~~~~~~ truncate -->
      <method access="public" instrs="21" name="truncate" static="yes" valid="no">
        <signature>
          <arg nr="1">
            <object>java.lang.String</object>
          </arg>
          <return>
            <object>java.lang.String</object>
          </return>
        </signature>
        <exceptions/>
        <summary/>
      </method>
      <!-- ~~~~~~~~~~~~~~~~~~~~~~~~~~~~~~~~~~~~~~~~~ useReloadingTestSuiteLoader -->
      <method access="protected" instrs="12" name="useReloadingTestSuiteLoader" valid="no">
        <signature>
          <return>
            <boolean/>
          </return>
        </signature>
        <exceptions/>
        <summary/>
      </method>
    </methods>
  </class>
  <copyright-notice>Copyright 2012-2019, Kestrel Technology LLC, Palo Alto, CA 94304</copyright-notice>
</codehawk-java-analyzer>
