<?xml version="1.0" encoding="UTF-8"?>
<codehawk-java-analyzer>
  <header info="class" time="2019-01-14 18:36:06"/>
  <class final="yes" name="Internal" package="com.google.protobuf">
    <interfaces/>
    <!-- ============================ CONSTRUCTORS ============================  -->
    <constructors>
      <!-- ~~~~~~~~~~~~~~~~~~~~~~~~~~~~~~~~~~~~~~~~~~~~~~~~~~~~~~~~~~~~~~~~~~ () -->
      <method access="private">
        <signature/>
        <exceptions/>
        <summary/>
      </method>
    </constructors>
    <!-- ============================== METHODS ==============================  -->
    <methods>
      <!-- ~~~~~~~~~~~~~~~~~~~~~~~~~~~~~~~~~~~~~~~~~~~~~~~ byteArrayDefaultValue -->
      <method access="public" name="byteArrayDefaultValue" static="yes">
        <signature>
          <arg nr="1">
            <object>java.lang.String</object>
          </arg>
          <return>
            <array>
              <byte/>
            </array>
          </return>
        </signature>
        <exceptions/>
        <summary/>
      </method>
      <!-- ~~~~~~~~~~~~~~~~~~~~~~~~~~~~~~~~~~~~~~~~~~~~~~ byteBufferDefaultValue -->
      <method access="public" name="byteBufferDefaultValue" static="yes">
        <signature>
          <arg nr="1">
            <object>java.lang.String</object>
          </arg>
          <return>
            <object>java.nio.ByteBuffer</object>
          </return>
        </signature>
        <exceptions/>
        <summary/>
      </method>
      <!-- ~~~~~~~~~~~~~~~~~~~~~~~~~~~~~~~~~~~~~~~~~~~~~~~~~~~ bytesDefaultValue -->
      <method access="public" name="bytesDefaultValue" static="yes">
        <signature>
          <arg nr="1">
            <object>java.lang.String</object>
          </arg>
          <return>
            <object>com.google.protobuf.ByteString</object>
          </return>
        </signature>
        <exceptions/>
        <summary/>
      </method>
      <!-- ~~~~~~~~~~~~~~~~~~~~~~~~~~~~~~~~~~~~~~~~~~~~~~~~~~~~~~~~ checkNotNull -->
      <method access="default" name="checkNotNull" static="yes">
        <signature>
          <arg nr="1">
            <object>java.lang.Object</object>
          </arg>
          <return>
            <object>java.lang.Object</object>
          </return>
        </signature>
        <exceptions/>
        <summary/>
      </method>
      <!-- ~~~~~~~~~~~~~~~~~~~~~~~~~~~~~~~~~~~~~~~~~~~~~~~~~~~~~~~~ checkNotNull -->
      <method access="default" name="checkNotNull" static="yes">
        <signature>
          <arg nr="1">
            <object>java.lang.Object</object>
          </arg>
          <arg nr="2">
            <object>java.lang.String</object>
          </arg>
          <return>
            <object>java.lang.Object</object>
          </return>
        </signature>
        <exceptions/>
        <summary/>
      </method>
      <!-- ~~~~~~~~~~~~~~~~~~~~~~~~~~~~~~~~~~~~~~~~~~~~~~~~~~~~~~ copyByteBuffer -->
      <method access="public" name="copyByteBuffer" static="yes">
        <signature>
          <arg nr="1">
            <object>java.nio.ByteBuffer</object>
          </arg>
          <return>
            <object>java.nio.ByteBuffer</object>
          </return>
        </signature>
        <exceptions/>
        <summary/>
      </method>
      <!-- ~~~~~~~~~~~~~~~~~~~~~~~~~~~~~~~~~~~~~~~~~~~~~~~~~~~~~~~~~~~~~~ equals -->
      <method access="public" name="equals" static="yes">
        <signature>
          <arg nr="1">
            <object>java.util.List</object>
          </arg>
          <arg nr="2">
            <object>java.util.List</object>
          </arg>
          <return>
            <boolean/>
          </return>
        </signature>
        <exceptions/>
        <summary/>
      </method>
      <!-- ~~~~~~~~~~~~~~~~~~~~~~~~~~~~~~~~~~~~~~~~~~~~~~~~~~~~ equalsByteBuffer -->
      <method access="public" name="equalsByteBuffer" static="yes">
        <signature>
          <arg nr="1">
            <object>java.nio.ByteBuffer</object>
          </arg>
          <arg nr="2">
            <object>java.nio.ByteBuffer</object>
          </arg>
          <return>
            <boolean/>
          </return>
        </signature>
        <exceptions/>
        <summary/>
      </method>
      <!-- ~~~~~~~~~~~~~~~~~~~~~~~~~~~~~~~~~~~~~~~~~~~~~~~~~~~~ equalsByteBuffer -->
      <method access="public" name="equalsByteBuffer" static="yes">
        <signature>
          <arg nr="1">
            <object>java.util.List</object>
          </arg>
          <arg nr="2">
            <object>java.util.List</object>
          </arg>
          <return>
            <boolean/>
          </return>
        </signature>
        <exceptions/>
        <summary/>
      </method>
      <!-- ~~~~~~~~~~~~~~~~~~~~~~~~~~~~~~~~~~~~~~~~~~~~~~~~~~ getDefaultInstance -->
      <method access="public" name="getDefaultInstance" static="yes">
        <signature>
          <arg nr="1">
            <object>java.lang.Class</object>
          </arg>
          <return>
            <object>com.google.protobuf.MessageLite</object>
          </return>
        </signature>
        <exceptions/>
        <summary/>
      </method>
      <!-- ~~~~~~~~~~~~~~~~~~~~~~~~~~~~~~~~~~~~~~~~~~~~~~~~~~~~~~~~~ hashBoolean -->
      <method access="public" name="hashBoolean" static="yes">
        <signature>
          <arg nr="1">
            <boolean/>
          </arg>
          <return>
            <int/>
          </return>
        </signature>
        <exceptions/>
        <summary/>
      </method>
      <!-- ~~~~~~~~~~~~~~~~~~~~~~~~~~~~~~~~~~~~~~~~~~~~~~~~~~~~~~~~~~~~ hashCode -->
      <method access="public" name="hashCode" static="yes">
        <signature>
          <arg nr="1">
            <object>java.util.List</object>
          </arg>
          <return>
            <int/>
          </return>
        </signature>
        <exceptions/>
        <summary/>
      </method>
      <!-- ~~~~~~~~~~~~~~~~~~~~~~~~~~~~~~~~~~~~~~~~~~~~~~~~~~~~~~~~~~~~ hashCode -->
      <method access="public" name="hashCode" static="yes">
        <signature>
          <arg nr="1">
            <array>
              <byte/>
            </array>
          </arg>
          <return>
            <int/>
          </return>
        </signature>
        <exceptions/>
        <summary/>
      </method>
      <!-- ~~~~~~~~~~~~~~~~~~~~~~~~~~~~~~~~~~~~~~~~~~~~~~~~~~~~~~~~~~~~ hashCode -->
      <method access="default" name="hashCode" static="yes">
        <signature>
          <arg nr="1">
            <array>
              <byte/>
            </array>
          </arg>
          <arg nr="2">
            <int/>
          </arg>
          <arg nr="3">
            <int/>
          </arg>
          <return>
            <int/>
          </return>
        </signature>
        <exceptions/>
        <summary/>
      </method>
      <!-- ~~~~~~~~~~~~~~~~~~~~~~~~~~~~~~~~~~~~~~~~~~~~~~~~~~ hashCodeByteBuffer -->
      <method access="public" name="hashCodeByteBuffer" static="yes">
        <signature>
          <arg nr="1">
            <object>java.util.List</object>
          </arg>
          <return>
            <int/>
          </return>
        </signature>
        <exceptions/>
        <summary/>
      </method>
      <!-- ~~~~~~~~~~~~~~~~~~~~~~~~~~~~~~~~~~~~~~~~~~~~~~~~~~ hashCodeByteBuffer -->
      <method access="public" name="hashCodeByteBuffer" static="yes">
        <signature>
          <arg nr="1">
            <object>java.nio.ByteBuffer</object>
          </arg>
          <return>
            <int/>
          </return>
        </signature>
        <exceptions/>
        <summary/>
      </method>
      <!-- ~~~~~~~~~~~~~~~~~~~~~~~~~~~~~~~~~~~~~~~~~~~~~~~~~~~~~~~~~~~~ hashEnum -->
      <method access="public" name="hashEnum" static="yes">
        <signature>
          <arg nr="1">
            <object>com.google.protobuf.Internal$EnumLite</object>
          </arg>
          <return>
            <int/>
          </return>
        </signature>
        <exceptions/>
        <summary/>
      </method>
      <!-- ~~~~~~~~~~~~~~~~~~~~~~~~~~~~~~~~~~~~~~~~~~~~~~~~~~~~~~~~ hashEnumList -->
      <method access="public" name="hashEnumList" static="yes">
        <signature>
          <arg nr="1">
            <object>java.util.List</object>
          </arg>
          <return>
            <int/>
          </return>
        </signature>
        <exceptions/>
        <summary/>
      </method>
      <!-- ~~~~~~~~~~~~~~~~~~~~~~~~~~~~~~~~~~~~~~~~~~~~~~~~~~~~~~~~~~~~ hashLong -->
      <method access="public" name="hashLong" static="yes">
        <signature>
          <arg nr="1">
            <long/>
          </arg>
          <return>
            <int/>
          </return>
        </signature>
        <exceptions/>
        <summary/>
      </method>
      <!-- ~~~~~~~~~~~~~~~~~~~~~~~~~~~~~~~~~~~~~~~~~~~~~~~~~~~~~~~~~ isValidUtf8 -->
      <method access="public" name="isValidUtf8" static="yes">
        <signature>
          <arg nr="1">
            <object>com.google.protobuf.ByteString</object>
          </arg>
          <return>
            <boolean/>
          </return>
        </signature>
        <exceptions/>
        <summary/>
      </method>
      <!-- ~~~~~~~~~~~~~~~~~~~~~~~~~~~~~~~~~~~~~~~~~~~~~~~~~~~~~~~~~ isValidUtf8 -->
      <method access="public" name="isValidUtf8" static="yes">
        <signature>
          <arg nr="1">
            <array>
              <byte/>
            </array>
          </arg>
          <return>
            <boolean/>
          </return>
        </signature>
        <exceptions/>
        <summary/>
      </method>
      <!-- ~~~~~~~~~~~~~~~~~~~~~~~~~~~~~~~~~~~~~~~~~~~~~~~~~~~~~~~~ mergeMessage -->
      <method access="default" name="mergeMessage" static="yes">
        <signature>
          <arg nr="1">
            <object>java.lang.Object</object>
          </arg>
          <arg nr="2">
            <object>java.lang.Object</object>
          </arg>
          <return>
            <object>java.lang.Object</object>
          </return>
        </signature>
        <exceptions/>
        <summary/>
      </method>
      <!-- ~~~~~~~~~~~~~~~~~~~~~~~~~~~~~~~~~~~~~~~~~~~~~~~~~~~~~~~~~ partialHash -->
      <method access="default" name="partialHash" static="yes">
        <signature>
          <arg nr="1">
            <int/>
          </arg>
          <arg nr="2">
            <array>
              <byte/>
            </array>
          </arg>
          <arg nr="3">
            <int/>
          </arg>
          <arg nr="4">
            <int/>
          </arg>
          <return>
            <int/>
          </return>
        </signature>
        <exceptions/>
        <summary/>
      </method>
      <!-- ~~~~~~~~~~~~~~~~~~~~~~~~~~~~~~~~~~~~~~~~~~~~~~~~~~ stringDefaultValue -->
      <method access="public" name="stringDefaultValue" static="yes">
        <signature>
          <arg nr="1">
            <object>java.lang.String</object>
          </arg>
          <return>
            <object>java.lang.String</object>
          </return>
        </signature>
        <exceptions/>
        <summary/>
      </method>
      <!-- ~~~~~~~~~~~~~~~~~~~~~~~~~~~~~~~~~~~~~~~~~~~~~~~~~~~~~~~~~ toByteArray -->
      <method access="public" name="toByteArray" static="yes">
        <signature>
          <arg nr="1">
            <object>java.lang.String</object>
          </arg>
          <return>
            <array>
              <byte/>
            </array>
          </return>
        </signature>
        <exceptions/>
        <summary/>
      </method>
      <!-- ~~~~~~~~~~~~~~~~~~~~~~~~~~~~~~~~~~~~~~~~~~~~~~~~~~~~~~~~ toStringUtf8 -->
      <method access="public" name="toStringUtf8" static="yes">
        <signature>
          <arg nr="1">
            <array>
              <byte/>
            </array>
          </arg>
          <return>
            <object>java.lang.String</object>
          </return>
        </signature>
        <exceptions/>
        <summary/>
      </method>
    </methods>
  </class>
  <copyright-notice>Copyright 2012-2019, Kestrel Technology LLC, Palo Alto, CA 94304</copyright-notice>
</codehawk-java-analyzer>
