<?xml version="1.0" encoding="UTF-8"?>
<codehawk-java-analyzer>
  <header info="interface" time="2020-04-01 10:44:40"/>
  <interface name="AbstractOrderedLayoutServerRpc" package="com.vaadin.shared.ui.orderedlayout">
    <superinterfaces>
      <superinterface>com.vaadin.shared.ui.LayoutClickRpc</superinterface>
      <superinterface>com.vaadin.shared.communication.ServerRpc</superinterface>
      <superinterface>java.io.Serializable</superinterface>
    </superinterfaces>
    <!-- =============================== FIELDS ===============================  -->
    <fields/>
    <!-- ============================== METHODS ==============================  -->
    <methods/>
  </interface>
  <copyright-notice>Copyright 2012-2020, Kestrel Technology LLC, Palo Alto, CA 94304</copyright-notice>
</codehawk-java-analyzer>
